qmss_sl_practice/.DS_Store
qmss_sl_practice/.gitignore
qmss_sl_practice/.readthedocs.yml
qmss_sl_practice/CONDUCT.rst
qmss_sl_practice/CONTRIBUTING.rst
qmss_sl_practice/LICENSE
qmss_sl_practice/README.md
qmss_sl_practice/docs/.DS_Store
qmss_sl_practice/docs/Makefile
qmss_sl_practice/docs/conduct.rst
qmss_sl_practice/docs/conf.py
qmss_sl_practice/docs/contributing.rst
qmss_sl_practice/docs/index.rst
qmss_sl_practice/docs/installation.rst
qmss_sl_practice/docs/make.bat
qmss_sl_practice/docs/source/modules.rst
qmss_sl_practice/docs/source/qmss_sl_practice.rst
qmss_sl_practice/docs/usage.rst
qmss_sl_practice/qmss_sl_practice/.DS_Store
qmss_sl_practice/qmss_sl_practice/__init__.py
qmss_sl_practice/qmss_sl_practice/qmss_sl_practice.py
qmss_sl_practice/tests/__init__.py
qmss_sl_practice/tests/test_qmss_sl_practice.py
qmss_sl_practice-0.1.0.dist-info/WHEEL
qmss_sl_practice-0.1.0.dist-info/METADATA
qmss_sl_practice-0.1.0.dist-info/RECORD
