Metadata-Version: 2.1
Name: qmss-sl-practice
Version: 0.1.0
Summary: This is a practice package.
License: MIT
Author: Shiying Lai
Author-email: sl4849@columbia.edu
Requires-Python: >=3.7,<4.0
Classifier: License :: OSI Approved :: MIT License
Classifier: Programming Language :: Python :: 3
Classifier: Programming Language :: Python :: 3.7
Classifier: Programming Language :: Python :: 3.8
Requires-Dist: pandas (>=1.1.4,<2.0.0)
